dataclassparse_txetx/__init__.py
dataclassparse_txetx/dataclassparse.py
dataclassparse_txetx-0.0.2.dist-info/licenses/LICENSE
dataclassparse_txetx-0.0.2.dist-info/METADATA
dataclassparse_txetx-0.0.2.dist-info/WHEEL
dataclassparse_txetx-0.0.2.dist-info/top_level.txt
dataclassparse_txetx-0.0.2.dist-info/RECORD
